{
	"partitions" : [
		{
			"name" : "Top",
			"pins" : [
				{
					"name" : "RegSrc[0]",
					"strict" : false
				},
				{
					"name" : "RegSrc[1]",
					"strict" : false
				},
				{
					"name" : "RegWrite",
					"strict" : false
				},
				{
					"name" : "ImmSrc[0]",
					"strict" : false
				},
				{
					"name" : "ImmSrc[1]",
					"strict" : false
				},
				{
					"name" : "ALUSrc",
					"strict" : false
				},
				{
					"name" : "ALUControl[0]",
					"strict" : false
				},
				{
					"name" : "ALUControl[1]",
					"strict" : false
				},
				{
					"name" : "MemWrite",
					"strict" : false
				},
				{
					"name" : "MemtoReg",
					"strict" : false
				},
				{
					"name" : "PCSrc",
					"strict" : false
				},
				{
					"name" : "Instr[27]",
					"strict" : false
				},
				{
					"name" : "Instr[20]",
					"strict" : false
				},
				{
					"name" : "Instr[26]",
					"strict" : false
				},
				{
					"name" : "Instr[28]",
					"strict" : false
				},
				{
					"name" : "Instr[29]",
					"strict" : false
				},
				{
					"name" : "Instr[30]",
					"strict" : false
				},
				{
					"name" : "Instr[31]",
					"strict" : false
				},
				{
					"name" : "Instr[25]",
					"strict" : false
				},
				{
					"name" : "Instr[22]",
					"strict" : false
				},
				{
					"name" : "Instr[24]",
					"strict" : false
				},
				{
					"name" : "Instr[23]",
					"strict" : false
				},
				{
					"name" : "Instr[12]",
					"strict" : false
				},
				{
					"name" : "Instr[13]",
					"strict" : false
				},
				{
					"name" : "Instr[14]",
					"strict" : false
				},
				{
					"name" : "Instr[15]",
					"strict" : false
				},
				{
					"name" : "ALUFlags[2]",
					"strict" : false
				},
				{
					"name" : "clk",
					"strict" : false
				},
				{
					"name" : "reset",
					"strict" : false
				},
				{
					"name" : "ALUFlags[1]",
					"strict" : false
				},
				{
					"name" : "ALUFlags[3]",
					"strict" : false
				},
				{
					"name" : "ALUFlags[0]",
					"strict" : false
				}
			]
		}
	]
}